frgeostat/__init__.py
frgeostat/cli.py
frgeostat/communes.py
frgeostat/config.toml
frgeostat/departements.py
frgeostat/utils.py
frgeostat-0.1.2.dist-info/METADATA
frgeostat-0.1.2.dist-info/WHEEL
frgeostat-0.1.2.dist-info/entry_points.txt
frgeostat-0.1.2.dist-info/RECORD
